Workbook

Sheet Procurement (P2P)
A1: PR_ID | B1: PO_ID | C1: Vendor | D1: Material | E1: Quantity | F1: Unit Price | G1: Total Cost | H1: Goods Received | I1: Payment Status | J1: Procurement Status
A2: PR001 | B2: PO001 | C2: ABC Supplier | D2: Laptop | E2: 5 | F2: 500 | G2: =E2*F2 -> 2500 | H2: Yes | I2: Paid | J2: =IF(AND(H2="Yes", I2="Paid"), "Completed", IF(H2="Yes", "In Process", "Pending")) -> Completed
A3: PR002 | B3: PO002 | C3: XYZ Supplier | D3: Mouse | E3: 20 | F3: 10 | G3: =E3*F3 -> 200 | H3: Yes | I3: Unpaid | J3: =IF(AND(H3="Yes", I3="Paid"), "Completed", IF(H3="Yes", "In Process", "Pending")) -> In Process
A4: PR003 | B4: PO003 | C4: ABC Supplier | D4: Keyboard | E4: 10 | F4: 20 | G4: =E4*F4 -> 200 | H4: No | I4: Unpaid | J4: =IF(AND(H4="Yes", I4="Paid"), "Completed", IF(H4="Yes", "In Process", "Pending")) -> Pending

Sheet Sales (O2C)
A1: SO_ID | B1: Customer | C1: Product | D1: Quantity | E1: Unit Price | F1: Revenue | G1: Delivery Status | H1: Payment Status | I1: Sales Status
A2: SO001 | B2: Rahim | C2: Laptop | D2: 2 | E2: 700 | F2: =D2*E2 -> 1400 | G2: Delivered | H2: Paid | I2: =IF(AND(G2="Delivered", H2="Paid"), "Closed", IF(G2="Delivered", "Awaiting Payment", "In Transit")) -> Closed
A3: SO002 | B3: Karim | C3: Mouse | D3: 5 | E3: 15 | F3: =D3*E3 -> 75 | G3: Delivered | H3: Paid | I3: =IF(AND(G3="Delivered", H3="Paid"), "Closed", IF(G3="Delivered", "Awaiting Payment", "In Transit")) -> Closed
A4: SO003 | B4: Hasan | C4: Keyboard | D4: 3 | E4: 30 | F4: =D4*E4 -> 90 | G4: Pending | H4: Unpaid | I4: =IF(AND(G4="Delivered", H4="Paid"), "Closed", IF(G4="Delivered", "Awaiting Payment", "In Transit")) -> In Transit

Sheet Inventory
A1: Material | B1: Opening Stock | C1: Purchased | D1: Sold | E1: Closing Stock | F1: Stock Health
A2: Laptop | B2: 10 | C2: =SUMIF('Procurement (P2P)'!D:D, A2, 'Procurement (P2P)'!E:E) -> 5 | D2: =SUMIF('Sales (O2C)'!C:C, A2, 'Sales (O2C)'!D:D) -> 2 | E2: =B2 + C2 - D2 -> 13 | F2: =IF(E2<5, "Low Stock", "OK") -> OK
A3: Mouse | B3: 50 | C3: =SUMIF('Procurement (P2P)'!D:D, A3, 'Procurement (P2P)'!E:E) -> 20 | D3: =SUMIF('Sales (O2C)'!C:C, A3, 'Sales (O2C)'!D:D) -> 5 | E3: =B3 + C3 - D3 -> 65 | F3: =IF(E3<5, "Low Stock", "OK") -> OK
A4: Keyboard | B4: 30 | C4: =SUMIF('Procurement (P2P)'!D:D, A4, 'Procurement (P2P)'!E:E) -> 10 | D4: =SUMIF('Sales (O2C)'!C:C, A4, 'Sales (O2C)'!D:D) -> 3 | E4: =B4 + C4 - D4 -> 37 | F4: =IF(E4<5, "Low Stock", "OK") -> OK
